genomespy/__about__.py
genomespy/__init__.py
genomespy/genomespy.py
genomespy/shared/cytobands.json
genomespy/shared/cytobands.tsv
genomespy/shared/genes.json
genomespy/shared/hg38.json
genomespy/shared/refSeq_genes_scored_compressed.hg38.tsv
genomespy-0.0.7.dist-info/METADATA
genomespy-0.0.7.dist-info/WHEEL
genomespy-0.0.7.dist-info/licenses/LICENSE.txt
genomespy-0.0.7.dist-info/RECORD
