Metadata-Version: 2.4
Name: genomespy
Version: 0.0.7
Summary: A python wrapper to the GPU-powered Javascript visualization grammar library GenomeSpy.
Project-URL: Documentation, https://github.com/fuxialexander/genomespy#readme
Project-URL: Issues, https://github.com/fuxialexander/genomespy/issues
Project-URL: Source, https://github.com/fuxialexander/genomespy
Author-email: fuxialexander <fuxialexander@gmail.com>
License-Expression: MIT
License-File: LICENSE.txt
Classifier: Development Status :: 4 - Beta
Classifier: Programming Language :: Python
Classifier: Programming Language :: Python :: 3.10
Classifier: Programming Language :: Python :: 3.11
Classifier: Programming Language :: Python :: 3.12
Classifier: Programming Language :: Python :: Implementation :: CPython
Classifier: Programming Language :: Python :: Implementation :: PyPy
Requires-Python: >=3.10
Requires-Dist: ipython
Requires-Dist: numpy
Requires-Dist: pandas
Requires-Dist: scipy
